CalculadoraDaniel/__init__.py
CalculadoraDaniel/calculadora.py
calc_daniel-0.1.0.dist-info/licenses/LICENSE
calc_daniel-0.1.0.dist-info/METADATA
calc_daniel-0.1.0.dist-info/WHEEL
calc_daniel-0.1.0.dist-info/top_level.txt
calc_daniel-0.1.0.dist-info/RECORD
